<?xml version="1.0" encoding="utf-8"?>
<databaseChangeLog
    xmlns="http://www.liquibase.org/xml/ns/dbchangelog"
    xmlns:xsi="http://www.w3.org/2001/XMLSchema-instance"
    xsi:schemaLocation="http://www.liquibase.org/xml/ns/dbchangelog http://www.liquibase.org/xml/ns/dbchangelog/dbchangelog-3.1.xsd">

    <property name="now" value="now()" dbms="mysql,h2"/>
    <property name="now" value="current_timestamp" dbms="postgresql"/>

    <!--
        Added the entity GoodWord.
    -->
    <changeSet id="20150301162626" author="jhipster">
        <createTable tableName="T_GOODWORD">
            <column name="id" type="bigint" autoIncrement="true">
                <constraints primaryKey="true" nullable="false"/>
            </column>
            <column name="value" type="varchar(255)"/>
            <column name="level" type="varchar(255)"/>
            <column name="badword_id" type="bigint"/>
        </createTable>
        
        <addForeignKeyConstraint baseColumnNames="badword_id"
                                 baseTableName="T_GOODWORD"
                                 constraintName="fk_goodword_badword_id"
                                 referencedColumnNames="id"
                                 referencedTableName="T_BADWORD"/>

    </changeSet>
</databaseChangeLog>
